endpoints_management/__init__.py
endpoints_management/auth/__init__.py
endpoints_management/auth/caches.py
endpoints_management/auth/suppliers.py
endpoints_management/auth/tokens.py
endpoints_management/config/__init__.py
endpoints_management/config/service_config.py
endpoints_management/control/__init__.py
endpoints_management/control/caches.py
endpoints_management/control/check_request.py
endpoints_management/control/client.py
endpoints_management/control/distribution.py
endpoints_management/control/label_descriptor.py
endpoints_management/control/metric_descriptor.py
endpoints_management/control/metric_value.py
endpoints_management/control/money.py
endpoints_management/control/operation.py
endpoints_management/control/path_regex.py
endpoints_management/control/quota_request.py
endpoints_management/control/report_request.py
endpoints_management/control/service.py
endpoints_management/control/signing.py
endpoints_management/control/timestamp.py
endpoints_management/control/wsgi.py
endpoints_management/control/vendor/__init__.py
endpoints_management/control/vendor/py3/__init__.py
endpoints_management/control/vendor/py3/sched.py
endpoints_management/gen/__init__.py
endpoints_management/gen/servicecontrol_v1_client.py
endpoints_management/gen/servicecontrol_v1_messages.py
endpoints_management/gen/servicemanagement_v1_messages.py
google_endpoints_api_management-1.11.0.dist-info/DESCRIPTION.rst
google_endpoints_api_management-1.11.0.dist-info/METADATA
google_endpoints_api_management-1.11.0.dist-info/RECORD
google_endpoints_api_management-1.11.0.dist-info/WHEEL
google_endpoints_api_management-1.11.0.dist-info/metadata.json
google_endpoints_api_management-1.11.0.dist-info/namespace_packages.txt
google_endpoints_api_management-1.11.0.dist-info/top_level.txt
