Metadata-Version: 1.1
Name: google-endpoints-api-management
Version: 1.11.0
Summary: Google Endpoints API management
Home-page: https://github.com/cloudendpoints/endpoints-management-python
Author: Google Inc
Author-email: googleapis-packages@google.com
License: Apache License
Platform: UNKNOWN
Classifier: Development Status :: 4 - Beta
Classifier: Intended Audience :: Developers
Classifier: License :: OSI Approved :: Apache Software License
Classifier: Programming Language :: Python
Classifier: Programming Language :: Python :: 2
Classifier: Programming Language :: Python :: 2.7
Classifier: Programming Language :: Python :: Implementation :: CPython
